alibabacloud_videoseg20200320/__init__.py
alibabacloud_videoseg20200320/client.py
alibabacloud_videoseg20200320/models.py
alibabacloud_videoseg20200320_py2-1.0.0.dist-info/LICENSE
alibabacloud_videoseg20200320_py2-1.0.0.dist-info/METADATA
alibabacloud_videoseg20200320_py2-1.0.0.dist-info/WHEEL
alibabacloud_videoseg20200320_py2-1.0.0.dist-info/top_level.txt
alibabacloud_videoseg20200320_py2-1.0.0.dist-info/RECORD
